Vulncapture/__init__.py
Vulncapture/dialogui.png
Vulncapture/mshei.ttf
Vulncapture/requirements.txt
Vulncapture/titlegui.png
Vulncapture-1.0.3.dist-info/LICENSE
Vulncapture-1.0.3.dist-info/METADATA
Vulncapture-1.0.3.dist-info/WHEEL
Vulncapture-1.0.3.dist-info/top_level.txt
Vulncapture-1.0.3.dist-info/RECORD
