Metadata-Version: 2.1
Name: Vulncapture
Version: 1.0.3
Summary: A capture moudle return base64 image
Author-email: jiangyangcreate <jiangyangcreate@gamil.com>
Project-URL: Homepage, https://github.com/jiangmiemie/Vulncapture
Project-URL: Bug Tracker, https://github.com/jiangmiemie/Vulncapture/issues
Classifier: Programming Language :: Python :: 3
Classifier: License :: OSI Approved :: MIT License
Classifier: Operating System :: OS Independent
Requires-Python: >=3.9
License-File: LICENSE
